cookiefilter/__init__.py
cookiefilter/middleware.py
django_cookiefilter-1.1.dist-info/licenses/LICENSE
django_cookiefilter-1.1.dist-info/METADATA
django_cookiefilter-1.1.dist-info/WHEEL
django_cookiefilter-1.1.dist-info/top_level.txt
django_cookiefilter-1.1.dist-info/RECORD
