Metadata-Version: 2.4
Name: django-cookiefilter
Version: 1.1
Summary: Django Cookie Filter
Maintainer-email: The Developer Society <studio@dev.ngo>
License-Expression: BSD-3-Clause
Project-URL: Homepage, https://github.com/developersociety/django-cookiefilter
Classifier: Environment :: Web Environment
Classifier: Framework :: Django
Classifier: Framework :: Django :: 3.2
Classifier: Framework :: Django :: 4.2
Classifier: Framework :: Django :: 5.2
Classifier: Intended Audience :: Developers
Classifier: Operating System :: OS Independent
Classifier: Programming Language :: Python
Classifier: Programming Language :: Python :: 3
Classifier: Programming Language :: Python :: 3.9
Classifier: Programming Language :: Python :: 3.10
Classifier: Programming Language :: Python :: 3.11
Classifier: Programming Language :: Python :: 3.12
Classifier: Programming Language :: Python :: 3.13
Requires-Python: >=3.9
License-File: LICENSE
Dynamic: license-file
